hashnode/hashnode.py
src/hashnode.py
hashnode-0.4.dev0.dist-info/LICENSE
hashnode-0.4.dev0.dist-info/METADATA
hashnode-0.4.dev0.dist-info/WHEEL
hashnode-0.4.dev0.dist-info/top_level.txt
hashnode-0.4.dev0.dist-info/RECORD
