Metadata-Version: 2.1
Name: hashnode
Version: 0.4.dev0
Summary: UNKNOWN
Home-page: https://github.com/JosiasAurel/python-hashnode
Author: Josias Aurel
Author-email: ndjosiasaurel@gmail.com
License: MIT
Platform: UNKNOWN
Requires-Dist: gql
